MANIFEST.in
setup.py
ckanext/__init__.py
ckanext/mapviews/__init__.py
ckanext/mapviews/plugin.py
ckanext/mapviews/theme/public/choroplethmap.css
ckanext/mapviews/theme/public/choroplethmap.js
ckanext/mapviews/theme/public/ckan_map_modules.js
ckanext/mapviews/theme/public/navigablemap.css
ckanext/mapviews/theme/public/navigablemap.js
ckanext/mapviews/theme/public/resource.config
ckanext/mapviews/theme/public/vendor/backend.ckan.js
ckanext/mapviews/theme/public/vendor/d3.scale.quantize.js
ckanext/mapviews/theme/public/vendor/excanvas.js
ckanext/mapviews/theme/public/vendor/leaflet.css
ckanext/mapviews/theme/public/vendor/leaflet.js
ckanext/mapviews/theme/public/vendor/leaflet.label.css
ckanext/mapviews/theme/public/vendor/leaflet.label.js
ckanext/mapviews/theme/public/vendor/queryStringToJSON.js
ckanext/mapviews/theme/templates/choroplethmap_form.html
ckanext/mapviews/theme/templates/choroplethmap_view.html
ckanext/mapviews/theme/templates/navigablemap_form.html
ckanext/mapviews/theme/templates/navigablemap_view.html
ckanext_mapviews.egg-info/PKG-INFO
ckanext_mapviews.egg-info/SOURCES.txt
ckanext_mapviews.egg-info/dependency_links.txt
ckanext_mapviews.egg-info/entry_points.txt
ckanext_mapviews.egg-info/namespace_packages.txt
ckanext_mapviews.egg-info/not-zip-safe
ckanext_mapviews.egg-info/pbr.json
ckanext_mapviews.egg-info/top_level.txt