Metadata-Version: 1.0
Name: ckanext-mapviews
Version: 0.1
Summary: Choropleth Map view for CKAN
Home-page: https://github.com/ckan/ckanext-mapviews
Author: Vitor Baptista
Author-email: vitor.baptista@okfn.org
License: UNKNOWN
Platform: UNKNOWN
